zone_file_parser/__init__.py
zone_file_parser/helper.py
zone_file_parser/parser.py
zone_file_parser/record.py
zone_file_parser-0.1.0.dist-info/METADATA
zone_file_parser-0.1.0.dist-info/WHEEL
zone_file_parser-0.1.0.dist-info/top_level.txt
zone_file_parser-0.1.0.dist-info/RECORD
