Metadata-Version: 2.1
Name: zone-file-parser
Version: 0.1.0
Summary: library for parsing dns zone files
Home-page: https://github.com/aredwood/zone-file-parser
Author: Alex Redwood
Author-email: hello@alexredwood.com
Maintainer: Alex Redwood
Maintainer-email: hello@alexredwood.com
License: MIT
Keywords: parse dns zone file
Platform: UNKNOWN
